gocd_cli-0.10.0-py2.7-nspkg.pth
gocd_cli-0.10.0.dist-info/METADATA
gocd_cli-0.10.0.dist-info/RECORD
gocd_cli-0.10.0.dist-info/WHEEL
gocd_cli-0.10.0.dist-info/metadata.json
gocd_cli-0.10.0.dist-info/top_level.txt
gocd_cli-0.10.0.dist-info/DESCRIPTION.rst
gocd_cli-0.10.0.dist-info/namespace_packages.txt
gocd_cli-0.10.0.data/scripts/gocd
gocd_cli/command.py
gocd_cli/exceptions.py
gocd_cli/settings.py
gocd_cli/utils.py
gocd_cli/encryption/caesar.py
gocd_cli/commands/settings.py
gocd_cli/commands/pipeline/retrigger_failed.py
gocd_cli/commands/pipeline/check.py
gocd_cli/commands/pipeline/__init__.py
