Metadata-Version: 2.0
Name: gocd-cli
Version: 0.10.0
Summary: A CLI client for interacting with Go Continuous Delivery
Home-page: https://github.com/gaqzi/gocd-cli/
Author: Björn Andersson
Author-email: ba@sanitarium.se
License: MIT License
Platform: UNKNOWN
Classifier: License :: OSI Approved :: MIT License
Classifier: Development Status :: 4 - Beta
Classifier: Operating System :: OS Independent
Classifier: Programming Language :: Python
Classifier: Programming Language :: Python :: 2
Classifier: Programming Language :: Python :: 2.6
Classifier: Programming Language :: Python :: 2.7
Requires-Dist: gocd (>=0.10.0,<1.0)
